airflow_declarative/__init__.py
airflow_declarative/builder.py
airflow_declarative/compat.py
airflow_declarative/operators.py
airflow_declarative/schema.py
airflow_declarative/trafaret.py
airflow_declarative/transformer.py
airflow_declarative-1.1.dist-info/LICENSE
airflow_declarative-1.1.dist-info/METADATA
airflow_declarative-1.1.dist-info/WHEEL
airflow_declarative-1.1.dist-info/top_level.txt
airflow_declarative-1.1.dist-info/RECORD
