Metadata-Version: 2.1
Name: airflow-declarative
Version: 1.1
Summary: Airflow DAGs done declaratively
Home-page: https://github.com/rambler-digital-solutions/airflow-declarative
Author: Usermodel @ Rambler&Co
Author-email: um@rambler-co.ru
Maintainer: Alexander Shorin
Maintainer-email: kxepal@gmail.com
License: Apache 2.0
Platform: UNKNOWN
Classifier: Development Status :: 4 - Beta
Classifier: Intended Audience :: Developers
Classifier: License :: OSI Approved :: Apache Software License
Classifier: Operating System :: MacOS :: MacOS X
Classifier: Operating System :: Microsoft :: Windows
Classifier: Operating System :: POSIX
Classifier: Programming Language :: Python
Classifier: Programming Language :: Python :: 3
Classifier: Programming Language :: Python :: 3.5
Classifier: Programming Language :: Python :: 3.6
Classifier: Programming Language :: Python :: 3.7
Classifier: Programming Language :: Python :: 3.8
Classifier: Topic :: Software Development :: Libraries
Requires-Python: >=2.7,!=3.0.*,!=3.1.*,!=3.2.*,!=3.3.*,!=3.4.*
Requires-Dist: croniter
Requires-Dist: jinja2 (>=2.8)
Requires-Dist: trafaret-config (==1.0.1)
Requires-Dist: trafaret (<2,>=1.0)
Requires-Dist: funcsigs ; python_version < "3"
Provides-Extra: develop
Requires-Dist: apache-airflow ; extra == 'develop'
Requires-Dist: coverage (==4.5.4) ; extra == 'develop'
Requires-Dist: flake8 (==3.7.8) ; extra == 'develop'
Requires-Dist: isort (==4.3.21) ; extra == 'develop'
Requires-Dist: mock (==2.0.0) ; extra == 'develop'
Requires-Dist: pytest (==4.6.6) ; extra == 'develop'
Requires-Dist: sphinx-rtd-theme (==0.4.3) ; extra == 'develop'
Requires-Dist: pylint (==2.4.2) ; (python_version >= "3") and extra == 'develop'
Requires-Dist: sphinx (==2.2.0) ; (python_version >= "3") and extra == 'develop'
Requires-Dist: black (==19.3b0) ; (python_version >= "3.6") and extra == 'develop'
